yt_audio_collector/__init__.py
yt_audio_collector/constants.py
yt_audio_collector/system_1/__init__.py
yt_audio_collector/system_1/fetch_youtube_data.py
yt_audio_collector/system_1/valid_transcript.py
yt_audio_collector/system_1/video_to_audio.py
yt_audio_collector/system_2/__init__.py
yt_audio_collector/system_2/preprocess_audio.py
yt_audio_collector/utils/__init__.py
yt_audio_collector/utils/file_utils.py
yt_audio_collector-0.1.0.dist-info/LICENSE
yt_audio_collector-0.1.0.dist-info/METADATA
yt_audio_collector-0.1.0.dist-info/WHEEL
yt_audio_collector-0.1.0.dist-info/RECORD
