Metadata-Version: 2.1
Name: yt_audio_collector
Version: 0.1.0
Summary: Create hindi language dataset for Speech Recognition from youtube
Home-page: https://github.com/Nagalakshmi136/yt_audio_collector
Keywords: hindi dataset,yt_audio_collector,youtube,youtube hindi audio,youtube hindi transcripts
Author: Mannasamudram Nagalakshmi
Requires-Python: >=3.9,<4.0
Classifier: License :: OSI Approved :: MIT License
Classifier: Operating System :: OS Independent
Classifier: Programming Language :: Python :: 3
Classifier: Programming Language :: Python :: 3.9
Classifier: Programming Language :: Python :: 3.10
Classifier: Programming Language :: Python :: 3.11
Classifier: Programming Language :: Python :: 3.12
Requires-Dist: google-api-python-client (>=2.98.0,<3.0.0)
Requires-Dist: librosa (>=0.10.1,<0.11.0)
Requires-Dist: numpy (>=1.18.5,<=1.26.0)
Requires-Dist: openai-whisper (>=20230918,<20230919)
Requires-Dist: pydub (>=0.25.1,<0.26.0)
Requires-Dist: pytube (>=15.0.0,<16.0.0)
Requires-Dist: soundfile (>=0.12.1,<0.13.0)
Requires-Dist: youtube-transcript-api (>=0.6.1,<0.7.0)
Project-URL: Documentation, https://nagalakshmi136.github.io/yt_audio_collector/
Project-URL: Repository, https://github.com/Nagalakshmi136/yt_audio_collector
